merge_files/__init__.py
merge_files/__main__.py
merge_files/main.py
merge_files/mergers/__init__.py
merge_files/mergers/concatenate.py
merge_files/mergers/env.py
merge_files-0.1.7.dist-info/entry_points.txt
merge_files-0.1.7.dist-info/WHEEL
merge_files-0.1.7.dist-info/METADATA
merge_files-0.1.7.dist-info/RECORD
